[
    {
        "id": "ABC001",
        "name": "Inicio"
    },
    {
        "id": "ABC002",
        "name": "Productos",
        "list": [
            {
                "id": 1,
                "name": "Libros"
            },
            {
                "id":2,
                "name": "Peliculas"
            },
            {
                "id":4,
                "name": "audioLibros"
            }
        ]
    },
    {
        "id": "ABC003",
        "name": "Contacto",
        "list": [
            {
                "id":1,
                "name":"Telefono"
            },
            {
                "id":2,
                "name":"Correo electronico"
            }

        ]
    },
    {
        "id": "ABC004",
        "name": "Sobre Nosotros"
    },
    {
        "id": "ABC005",
        "name": "Otro Nuevo",
        "list": [
            {
                "id":1,
                "name":"otra cosa1"
            },
            {
                "id":2,
                "name":"otra cosa2"
            }
        ]
    }
]
